napari_input_visualizer/__init__.py
napari_input_visualizer/_widget.py
napari_input_visualizer/napari.yaml
napari_input_visualizer-0.0.1.dist-info/LICENSE
napari_input_visualizer-0.0.1.dist-info/METADATA
napari_input_visualizer-0.0.1.dist-info/WHEEL
napari_input_visualizer-0.0.1.dist-info/entry_points.txt
napari_input_visualizer-0.0.1.dist-info/top_level.txt
napari_input_visualizer-0.0.1.dist-info/RECORD
