Metadata-Version: 2.1
Name: napari-input-visualizer
Version: 0.0.1
Summary: Visualize keyboard and mouse button presses
Home-page: https://github.com/bauerdavid/napari-input-visualizer
Author: David Bauer
Author-email: dbauer@brc.hu
License: BSD-3-Clause
Project-URL: Bug Tracker, https://github.com/bauerdavid/napari-input-visualizer/issues
Project-URL: Documentation, https://github.com/bauerdavid/napari-input-visualizer#README.md
Project-URL: Source Code, https://github.com/bauerdavid/napari-input-visualizer
Project-URL: User Support, https://github.com/bauerdavid/napari-input-visualizer/issues
Classifier: Development Status :: 2 - Pre-Alpha
Classifier: Framework :: napari
Classifier: Intended Audience :: Developers
Classifier: License :: OSI Approved :: BSD License
Classifier: Operating System :: OS Independent
Classifier: Programming Language :: Python
Classifier: Programming Language :: Python :: 3
Classifier: Programming Language :: Python :: 3 :: Only
Classifier: Programming Language :: Python :: 3.8
Classifier: Programming Language :: Python :: 3.9
Classifier: Programming Language :: Python :: 3.10
Classifier: Topic :: Scientific/Engineering :: Image Processing
Requires-Python: >=3.8
License-File: LICENSE
Requires-Dist: numpy
Requires-Dist: magicgui
Requires-Dist: qtpy
Requires-Dist: napari
Requires-Dist: imageio-ffmpeg
Provides-Extra: testing
Requires-Dist: tox ; extra == 'testing'
Requires-Dist: pytest ; extra == 'testing'
Requires-Dist: pytest-cov ; extra == 'testing'
Requires-Dist: pytest-qt ; extra == 'testing'
Requires-Dist: napari ; extra == 'testing'
Requires-Dist: pyqt5 ; extra == 'testing'
